{
    "id": "v280",
    "version": "v2.8.0",
    "badge": "stable",
    "name": "Image Editor Tool",
    "date": "March 2026",
    "isCurrent": false,
    "open": false,
    "counts": {
        "new": 1
    },
    "categories": [
        {
            "label": "New Tools",
            "features": [
                {
                    "type": "new",
                    "label": "Image Editor",
                    "desc": "Full image editor with header (undo/redo, rotate, flip, zoom, save dropdown), left toolbar (10 tools: select, crop, rotate, resize, adjust, filter, draw, eraser, text, overlay), right context panel, canvas with zoom/pan, footer with live info. Keyboard shortcuts for all actions. Saves to Downloads panel.",
                    "howto": "DevHub \u2192 Image Editor \u2192 Drop or open any image"
                }
            ]
        }
    ]
}